AUTHORS.md
CHANGES.md
MANIFEST.in
README.md
requirements.txt
setup.py
django_q_email/__init__.py
django_q_email/backends.py
django_q_email/utils.py
django_q_email.egg-info/PKG-INFO
django_q_email.egg-info/SOURCES.txt
django_q_email.egg-info/dependency_links.txt
django_q_email.egg-info/not-zip-safe
django_q_email.egg-info/requires.txt
django_q_email.egg-info/top_level.txt