Metadata-Version: 1.0
Name: django-q-email
Version: 5.0.1
Summary: Queues the sending of email with Django Q.
Home-page: http://github.com/joeyespo/django-q-email
Author: Joe Esposito
Author-email: joe@joeyespo.com
License: MIT
Platform: any
